videosdk/plugins/groq/__init__.py
videosdk/plugins/groq/tts.py
videosdk/plugins/groq/version.py
videosdk_plugins_groq-0.0.58.dist-info/METADATA
videosdk_plugins_groq-0.0.58.dist-info/WHEEL
videosdk_plugins_groq-0.0.58.dist-info/RECORD
